apollo/__init__.py
apollo/client.py
apollo/decorators.py
apollo/exceptions.py
apollo/util.py
apollo/annotations/__init__.py
apollo/cannedcomments/__init__.py
apollo/cannedkeys/__init__.py
apollo/cannedvalues/__init__.py
apollo/groups/__init__.py
apollo/io/__init__.py
apollo/metrics/__init__.py
apollo/organisms/__init__.py
apollo/remote/__init__.py
apollo/status/__init__.py
apollo/users/__init__.py
arrow/__init__.py
arrow/apollo.py
arrow/cli.py
arrow/config.py
arrow/decorators.py
arrow/io.py
arrow/commands/__init__.py
arrow/commands/cmd_annotations.py
arrow/commands/cmd_cannedcomments.py
arrow/commands/cmd_cannedkeys.py
arrow/commands/cmd_cannedvalues.py
arrow/commands/cmd_groups.py
arrow/commands/cmd_init.py
arrow/commands/cmd_io.py
arrow/commands/cmd_metrics.py
arrow/commands/cmd_organisms.py
arrow/commands/cmd_remote.py
arrow/commands/cmd_status.py
arrow/commands/cmd_users.py
arrow/commands/annotations/__init__.py
arrow/commands/annotations/add_attribute.py
arrow/commands/annotations/add_comment.py
arrow/commands/annotations/add_dbxref.py
arrow/commands/annotations/add_feature.py
arrow/commands/annotations/add_features.py
arrow/commands/annotations/add_transcript.py
arrow/commands/annotations/add_transcripts.py
arrow/commands/annotations/delete_attribute.py
arrow/commands/annotations/delete_dbxref.py
arrow/commands/annotations/delete_feature.py
arrow/commands/annotations/delete_sequence_alteration.py
arrow/commands/annotations/duplicate_transcript.py
arrow/commands/annotations/flip_strand.py
arrow/commands/annotations/get_comments.py
arrow/commands/annotations/get_feature_sequence.py
arrow/commands/annotations/get_features.py
arrow/commands/annotations/get_gff3.py
arrow/commands/annotations/get_search_tools.py
arrow/commands/annotations/get_sequence_alterations.py
arrow/commands/annotations/load_gff3.py
arrow/commands/annotations/load_legacy_gff3.py
arrow/commands/annotations/merge_exons.py
arrow/commands/annotations/set_boundaries.py
apollo-4.2.13.dist-info/LICENSE.txt
apollo-4.2.13.dist-info/METADATA
apollo-4.2.13.dist-info/WHEEL
apollo-4.2.13.dist-info/entry_points.txt
apollo-4.2.13.dist-info/top_level.txt
apollo-4.2.13.dist-info/RECORD
