Metadata-Version: 2.1
Name: apollo
Version: 4.2.13
Summary: Apollo API library
Home-page: https://github.com/galaxy-genome-annotation/python-apollo
Author: Helena Rasche;Anthony Bretaudeau;Nathan Dunn
Author-email: hxr@hx42.org
License: MIT
Platform: UNKNOWN
Classifier: Development Status :: 4 - Beta
Classifier: Intended Audience :: Developers
Classifier: License :: OSI Approved :: MIT License
Classifier: Operating System :: OS Independent
Classifier: Topic :: Scientific/Engineering
Classifier: Programming Language :: Python :: 3.7
License-File: LICENSE.txt
Requires-Dist: requests
Requires-Dist: biopython (>=1.77)
Requires-Dist: cachetools (<4)
Requires-Dist: click (>=6.7)
Requires-Dist: wrapt
Requires-Dist: pyyaml
Requires-Dist: decorator
Requires-Dist: bcbio-gff (>=0.6.6)
